py2pyd/__init__.py
py2pyd/compiler.py
py2pyd-0.1.4.dist-info/METADATA
py2pyd-0.1.4.dist-info/WHEEL
py2pyd-0.1.4.dist-info/entry_points.txt
py2pyd-0.1.4.dist-info/top_level.txt
py2pyd-0.1.4.dist-info/RECORD
