Metadata-Version: 2.2
Name: py2pyd
Version: 0.1.4
Summary: Cross-platform .py file to shared library(dll) compiler, .pyd (Windows) or .so (Linux).
Home-page: https://github.com/sachadee/py2pyd
Author: Sacha Dehe
Author-email: sachadehe@gmail.com
Classifier: Programming Language :: Python :: 3
Classifier: Operating System :: Microsoft :: Windows
Classifier: Operating System :: POSIX :: Linux
Requires-Python: >=3.6
Requires-Dist: Cython
Requires-Dist: setuptools
Dynamic: author
Dynamic: author-email
Dynamic: classifier
Dynamic: description
Dynamic: description-content-type
Dynamic: home-page
Dynamic: requires-dist
Dynamic: requires-python
Dynamic: summary
